aioservertiming/__init__.py
aioservertiming-0.0.1a1.dist-info/LICENSE
aioservertiming-0.0.1a1.dist-info/METADATA
aioservertiming-0.0.1a1.dist-info/WHEEL
aioservertiming-0.0.1a1.dist-info/top_level.txt
aioservertiming-0.0.1a1.dist-info/RECORD
