Metadata-Version: 2.1
Name: aioservertiming
Version: 0.0.1a1
Summary: Server Timing interaction for aiohttp
Home-page: https://github.com/jorektheglitch/aioservertiming
Author: jorektheglitch
Author-email: jorektheglitch@yandex.ru
License: UNKNOWN
Platform: UNKNOWN
Classifier: Programming Language :: Python :: 3
Classifier: Operating System :: OS Independent
Requires-Python: >=3.6
